[
  {
    "year": 1945,
    "z": 0,
    "sa_1": 1.0,
    "sa_2": 0.0,
    "sa_3": 0.0,
    "sa_4": 0.0
  },
  {
    "year": 1945,
    "z": 1,
    "sa_1": NaN,
    "sa_2": NaN,
    "sa_3": NaN,
    "sa_4": NaN
  },
  {
    "year": 1946,
    "z": 0,
    "sa_1": 0.0,
    "sa_2": 0.0,
    "sa_3": 1.0,
    "sa_4": 0.0
  },
  {
    "year": 1946,
    "z": 1,
    "sa_1": NaN,
    "sa_2": NaN,
    "sa_3": NaN,
    "sa_4": NaN
  },
  {
    "year": 1948,
    "z": 0,
    "sa_1": 1.0,
    "sa_2": 0.0,
    "sa_3": 0.0,
    "sa_4": 0.0
  },
  {
    "year": 1948,
    "z": 1,
    "sa_1": NaN,
    "sa_2": NaN,
    "sa_3": NaN,
    "sa_4": NaN
  },
  {
    "year": 1949,
    "z": 0,
    "sa_1": 0.0,
    "sa_2": 0.0,
    "sa_3": 1.0,
    "sa_4": 0.0
  },
  {
    "year": 1949,
    "z": 1,
    "sa_1": NaN,
    "sa_2": NaN,
    "sa_3": NaN,
    "sa_4": NaN
  },
  {
    "year": 1950,
    "z": 0,
    "sa_1": 0.5,
    "sa_2": 0.5,
    "sa_3": 0.0,
    "sa_4": 0.0
  },
  {
    "year": 1950,
    "z": 1,
    "sa_1": NaN,
    "sa_2": NaN,
    "sa_3": NaN,
    "sa_4": NaN
  },
  {
    "year": 1951,
    "z": 0,
    "sa_1": 0.5,
    "sa_2": 0.5,
    "sa_3": 0.0,
    "sa_4": 0.0
  },
  {
    "year": 1951,
    "z": 1,
    "sa_1": 0.3333333333333333,
    "sa_2": 0.6666666666666666,
    "sa_3": 0.0,
    "sa_4": 0.0
  },
  {
    "year": 1952,
    "z": 0,
    "sa_1": 0.6666666666666666,
    "sa_2": 0.3333333333333333,
    "sa_3": 0.0,
    "sa_4": 0.0
  },
  {
    "year": 1952,
    "z": 1,
    "sa_1": 0.0,
    "sa_2": 0.0,
    "sa_3": 1.0,
    "sa_4": 0.0
  },
  {
    "year": 1953,
    "z": 0,
    "sa_1": 0.3333333333333333,
    "sa_2": 0.3333333333333333,
    "sa_3": 0.3333333333333333,
    "sa_4": 0.0
  },
  {
    "year": 1953,
    "z": 1,
    "sa_1": NaN,
    "sa_2": NaN,
    "sa_3": NaN,
    "sa_4": NaN
  },
  {
    "year": 1954,
    "z": 0,
    "sa_1": 0.2,
    "sa_2": 0.4,
    "sa_3": 0.2,
    "sa_4": 0.2
  },
  {
    "year": 1954,
    "z": 1,
    "sa_1": 0.6666666666666666,
    "sa_2": 0.3333333333333333,
    "sa_3": 0.0,
    "sa_4": 0.0
  },
  {
    "year": 1955,
    "z": 0,
    "sa_1": 0.5,
    "sa_2": 0.5,
    "sa_3": 0.0,
    "sa_4": 0.0
  },
  {
    "year": 1955,
    "z": 1,
    "sa_1": 0.2,
    "sa_2": 0.4,
    "sa_3": 0.4,
    "sa_4": 0.0
  },
  {
    "year": 1956,
    "z": 0,
    "sa_1": 0.2,
    "sa_2": 0.8,
    "sa_3": 0.0,
    "sa_4": 0.0
  },
  {
    "year": 1956,
    "z": 1,
    "sa_1": 0.3333333333333333,
    "sa_2": 0.6666666666666666,
    "sa_3": 0.0,
    "sa_4": 0.0
  },
  {
    "year": 1957,
    "z": 0,
    "sa_1": 0.25,
    "sa_2": 0.5,
    "sa_3": 0.0,
    "sa_4": 0.25
  },
  {
    "year": 1957,
    "z": 1,
    "sa_1": NaN,
    "sa_2": NaN,
    "sa_3": NaN,
    "sa_4": NaN
  },
  {
    "year": 1958,
    "z": 0,
    "sa_1": 0.2727272727272727,
    "sa_2": 0.6363636363636364,
    "sa_3": 0.09090909090909091,
    "sa_4": 0.0
  },
  {
    "year": 1958,
    "z": 1,
    "sa_1": 0.6666666666666666,
    "sa_2": 0.3333333333333333,
    "sa_3": 0.0,
    "sa_4": 0.0
  },
  {
    "year": 1959,
    "z": 0,
    "sa_1": 0.25,
    "sa_2": 0.625,
    "sa_3": 0.0,
    "sa_4": 0.125
  },
  {
    "year": 1959,
    "z": 1,
    "sa_1": 0.3333333333333333,
    "sa_2": 0.6666666666666666,
    "sa_3": 0.0,
    "sa_4": 0.0
  },
  {
    "year": 1960,
    "z": 0,
    "sa_1": 0.3333333333333333,
    "sa_2": 0.47619047619047616,
    "sa_3": 0.09523809523809523,
    "sa_4": 0.09523809523809523
  },
  {
    "year": 1960,
    "z": 1,
    "sa_1": 0.0,
    "sa_2": 0.0,
    "sa_3": 1.0,
    "sa_4": 0.0
  },
  {
    "year": 1961,
    "z": 0,
    "sa_1": 0.5238095238095238,
    "sa_2": 0.3333333333333333,
    "sa_3": 0.09523809523809523,
    "sa_4": 0.047619047619047616
  },
  {
    "year": 1961,
    "z": 1,
    "sa_1": 0.3125,
    "sa_2": 0.5,
    "sa_3": 0.1875,
    "sa_4": 0.0
  },
  {
    "year": 1962,
    "z": 0,
    "sa_1": 0.42105263157894735,
    "sa_2": 0.42105263157894735,
    "sa_3": 0.15789473684210525,
    "sa_4": 0.0
  },
  {
    "year": 1962,
    "z": 1,
    "sa_1": 0.5238095238095238,
    "sa_2": 0.23809523809523808,
    "sa_3": 0.09523809523809523,
    "sa_4": 0.14285714285714285
  },
  {
    "year": 1963,
    "z": 0,
    "sa_1": 0.38095238095238093,
    "sa_2": 0.19047619047619047,
    "sa_3": 0.3333333333333333,
    "sa_4": 0.09523809523809523
  },
  {
    "year": 1963,
    "z": 1,
    "sa_1": 0.4,
    "sa_2": 0.4,
    "sa_3": 0.0,
    "sa_4": 0.2
  },
  {
    "year": 1964,
    "z": 0,
    "sa_1": 0.1111111111111111,
    "sa_2": 0.19444444444444445,
    "sa_3": 0.4166666666666667,
    "sa_4": 0.2777777777777778
  },
  {
    "year": 1964,
    "z": 1,
    "sa_1": 0.08695652173913043,
    "sa_2": 0.4782608695652174,
    "sa_3": 0.13043478260869565,
    "sa_4": 0.30434782608695654
  },
  {
    "year": 1965,
    "z": 0,
    "sa_1": 0.2777777777777778,
    "sa_2": 0.16666666666666666,
    "sa_3": 0.4444444444444444,
    "sa_4": 0.1111111111111111
  },
  {
    "year": 1965,
    "z": 1,
    "sa_1": 0.3333333333333333,
    "sa_2": 0.21212121212121213,
    "sa_3": 0.2727272727272727,
    "sa_4": 0.18181818181818182
  },
  {
    "year": 1966,
    "z": 0,
    "sa_1": 0.391304347826087,
    "sa_2": 0.45652173913043476,
    "sa_3": 0.15217391304347827,
    "sa_4": 0.0
  },
  {
    "year": 1966,
    "z": 1,
    "sa_1": 0.5882352941176471,
    "sa_2": 0.3333333333333333,
    "sa_3": 0.058823529411764705,
    "sa_4": 0.0196078431372549
  },
  {
    "year": 1967,
    "z": 0,
    "sa_1": 0.6730769230769231,
    "sa_2": 0.19230769230769232,
    "sa_3": 0.1346153846153846,
    "sa_4": 0.0
  },
  {
    "year": 1967,
    "z": 1,
    "sa_1": 0.5,
    "sa_2": 0.29411764705882354,
    "sa_3": 0.17647058823529413,
    "sa_4": 0.029411764705882353
  },
  {
    "year": 1968,
    "z": 0,
    "sa_1": 0.5714285714285714,
    "sa_2": 0.2857142857142857,
    "sa_3": 0.08163265306122448,
    "sa_4": 0.061224489795918366
  },
  {
    "year": 1968,
    "z": 1,
    "sa_1": 0.48,
    "sa_2": 0.35,
    "sa_3": 0.16,
    "sa_4": 0.01
  },
  {
    "year": 1969,
    "z": 0,
    "sa_1": 0.46808510638297873,
    "sa_2": 0.3617021276595745,
    "sa_3": 0.1595744680851064,
    "sa_4": 0.010638297872340425
  },
  {
    "year": 1969,
    "z": 1,
    "sa_1": 0.42857142857142855,
    "sa_2": 0.39097744360902253,
    "sa_3": 0.13533834586466165,
    "sa_4": 0.045112781954887216
  },
  {
    "year": 1970,
    "z": 0,
    "sa_1": 0.6336633663366337,
    "sa_2": 0.26732673267326734,
    "sa_3": 0.0594059405940594,
    "sa_4": 0.039603960396039604
  },
  {
    "year": 1970,
    "z": 1,
    "sa_1": 0.49624060150375937,
    "sa_2": 0.3082706766917293,
    "sa_3": 0.11278195488721804,
    "sa_4": 0.08270676691729323
  },
  {
    "year": 1971,
    "z": 0,
    "sa_1": 0.43859649122807015,
    "sa_2": 0.43859649122807015,
    "sa_3": 0.11695906432748537,
    "sa_4": 0.005847953216374269
  },
  {
    "year": 1971,
    "z": 1,
    "sa_1": 0.45054945054945056,
    "sa_2": 0.3516483516483517,
    "sa_3": 0.14835164835164835,
    "sa_4": 0.04945054945054945
  },
  {
    "year": 1972,
    "z": 0,
    "sa_1": 0.45408163265306123,
    "sa_2": 0.3979591836734694,
    "sa_3": 0.11734693877551021,
    "sa_4": 0.030612244897959183
  },
  {
    "year": 1972,
    "z": 1,
    "sa_1": 0.4558139534883721,
    "sa_2": 0.3674418604651163,
    "sa_3": 0.13488372093023257,
    "sa_4": 0.04186046511627907
  },
  {
    "year": 1973,
    "z": 0,
    "sa_1": 0.48739495798319327,
    "sa_2": 0.3487394957983193,
    "sa_3": 0.14285714285714285,
    "sa_4": 0.02100840336134454
  },
  {
    "year": 1973,
    "z": 1,
    "sa_1": 0.44313725490196076,
    "sa_2": 0.39215686274509803,
    "sa_3": 0.13333333333333333,
    "sa_4": 0.03137254901960784
  },
  {
    "year": 1974,
    "z": 0,
    "sa_1": 0.4411764705882353,
    "sa_2": 0.3627450980392157,
    "sa_3": 0.14705882352941177,
    "sa_4": 0.049019607843137254
  },
  {
    "year": 1974,
    "z": 1,
    "sa_1": 0.43478260869565216,
    "sa_2": 0.3536231884057971,
    "sa_3": 0.17391304347826086,
    "sa_4": 0.03768115942028986
  },
  {
    "year": 1975,
    "z": 0,
    "sa_1": 0.44745762711864406,
    "sa_2": 0.3389830508474576,
    "sa_3": 0.18305084745762712,
    "sa_4": 0.030508474576271188
  },
  {
    "year": 1975,
    "z": 1,
    "sa_1": 0.530791788856305,
    "sa_2": 0.31085043988269795,
    "sa_3": 0.11730205278592376,
    "sa_4": 0.04105571847507331
  },
  {
    "year": 1976,
    "z": 0,
    "sa_1": 0.5218508997429306,
    "sa_2": 0.33676092544987146,
    "sa_3": 0.11311053984575835,
    "sa_4": 0.028277634961439587
  },
  {
    "year": 1976,
    "z": 1,
    "sa_1": 0.5271867612293144,
    "sa_2": 0.3073286052009456,
    "sa_3": 0.12293144208037825,
    "sa_4": 0.0425531914893617
  },
  {
    "year": 1977,
    "z": 0,
    "sa_1": 0.5067567567567568,
    "sa_2": 0.3536036036036036,
    "sa_3": 0.10810810810810811,
    "sa_4": 0.03153153153153153
  },
  {
    "year": 1977,
    "z": 1,
    "sa_1": 0.48987108655616945,
    "sa_2": 0.34990791896869244,
    "sa_3": 0.13627992633517497,
    "sa_4": 0.02394106813996317
  },
  {
    "year": 1978,
    "z": 0,
    "sa_1": 0.5370370370370371,
    "sa_2": 0.3111111111111111,
    "sa_3": 0.12777777777777777,
    "sa_4": 0.024074074074074074
  },
  {
    "year": 1978,
    "z": 1,
    "sa_1": 0.5122749590834698,
    "sa_2": 0.353518821603928,
    "sa_3": 0.10638297872340426,
    "sa_4": 0.027823240589198037
  },
  {
    "year": 1979,
    "z": 0,
    "sa_1": 0.47753743760399336,
    "sa_2": 0.34442595673876875,
    "sa_3": 0.13477537437603992,
    "sa_4": 0.04326123128119801
  },
  {
    "year": 1979,
    "z": 1,
    "sa_1": 0.49239280774550487,
    "sa_2": 0.355463347164592,
    "sa_3": 0.11479944674965421,
    "sa_4": 0.03734439834024896
  },
  {
    "year": 1980,
    "z": 0,
    "sa_1": 0.47531734837799716,
    "sa_2": 0.3511988716502116,
    "sa_3": 0.1368124118476728,
    "sa_4": 0.036671368124118475
  },
  {
    "year": 1980,
    "z": 1,
    "sa_1": 0.5431145431145431,
    "sa_2": 0.3256113256113256,
    "sa_3": 0.10810810810810811,
    "sa_4": 0.023166023166023165
  },
  {
    "year": 1981,
    "z": 0,
    "sa_1": 0.51278928136419,
    "sa_2": 0.32521315468940315,
    "sa_3": 0.13276492082825822,
    "sa_4": 0.029232643118148598
  },
  {
    "year": 1981,
    "z": 1,
    "sa_1": 0.5021645021645021,
    "sa_2": 0.3528138528138528,
    "sa_3": 0.11363636363636363,
    "sa_4": 0.031385281385281384
  },
  {
    "year": 1982,
    "z": 0,
    "sa_1": 0.4973544973544973,
    "sa_2": 0.3492063492063492,
    "sa_3": 0.1291005291005291,
    "sa_4": 0.02433862433862434
  },
  {
    "year": 1982,
    "z": 1,
    "sa_1": 0.4903660886319846,
    "sa_2": 0.34296724470134876,
    "sa_3": 0.1329479768786127,
    "sa_4": 0.03371868978805395
  },
  {
    "year": 1983,
    "z": 0,
    "sa_1": 0.5093833780160858,
    "sa_2": 0.33065236818588023,
    "sa_3": 0.13762287756925826,
    "sa_4": 0.022341376228775692
  },
  {
    "year": 1983,
    "z": 1,
    "sa_1": 0.4911541701769166,
    "sa_2": 0.3243470935130581,
    "sa_3": 0.15585509688289806,
    "sa_4": 0.02864363942712721
  },
  {
    "year": 1984,
    "z": 0,
    "sa_1": 0.4856396866840731,
    "sa_2": 0.3394255874673629,
    "sa_3": 0.1462140992167102,
    "sa_4": 0.028720626631853787
  },
  {
    "year": 1984,
    "z": 1,
    "sa_1": 0.48564954682779454,
    "sa_2": 0.3285498489425982,
    "sa_3": 0.14425981873111782,
    "sa_4": 0.04154078549848943
  },
  {
    "year": 1985,
    "z": 0,
    "sa_1": 0.47691247415575466,
    "sa_2": 0.35354927636113026,
    "sa_3": 0.14266023432115782,
    "sa_4": 0.026878015161957272
  },
  {
    "year": 1985,
    "z": 1,
    "sa_1": 0.47485303723056826,
    "sa_2": 0.34944480731548005,
    "sa_3": 0.14435009797517961,
    "sa_4": 0.031352057478772045
  },
  {
    "year": 1986,
    "z": 0,
    "sa_1": 0.49558638083228246,
    "sa_2": 0.341109709962169,
    "sa_3": 0.13366960907944514,
    "sa_4": 0.029634300126103404
  },
  {
    "year": 1986,
    "z": 1,
    "sa_1": 0.4688067837674137,
    "sa_2": 0.34039975772259234,
    "sa_3": 0.15263476680799515,
    "sa_4": 0.03815869170199879
  },
  {
    "year": 1987,
    "z": 0,
    "sa_1": 0.4487671232876712,
    "sa_2": 0.3747945205479452,
    "sa_3": 0.14191780821917807,
    "sa_4": 0.03452054794520548
  },
  {
    "year": 1987,
    "z": 1,
    "sa_1": 0.43445878848063557,
    "sa_2": 0.3624627606752731,
    "sa_3": 0.16385302879841113,
    "sa_4": 0.03922542204568024
  },
  {
    "year": 1988,
    "z": 0,
    "sa_1": 0.4316378908072795,
    "sa_2": 0.36957536164255717,
    "sa_3": 0.16098926738217453,
    "sa_4": 0.0377974801679888
  },
  {
    "year": 1988,
    "z": 1,
    "sa_1": 0.4178173719376392,
    "sa_2": 0.36124721603563476,
    "sa_3": 0.18129175946547885,
    "sa_4": 0.03964365256124722
  },
  {
    "year": 1989,
    "z": 0,
    "sa_1": 0.41494149414941495,
    "sa_2": 0.3631863186318632,
    "sa_3": 0.17281728172817282,
    "sa_4": 0.049054905490549056
  },
  {
    "year": 1989,
    "z": 1,
    "sa_1": 0.40787853918752565,
    "sa_2": 0.3647927780057448,
    "sa_3": 0.1719327041444399,
    "sa_4": 0.0553959786622897
  },
  {
    "year": 1990,
    "z": 0,
    "sa_1": 0.45018757815756566,
    "sa_2": 0.34389328887036263,
    "sa_3": 0.16340141725719048,
    "sa_4": 0.0425177157148812
  },
  {
    "year": 1990,
    "z": 1,
    "sa_1": 0.39861218195836545,
    "sa_2": 0.361603700848111,
    "sa_3": 0.176946800308404,
    "sa_4": 0.06283731688511951
  },
  {
    "year": 1991,
    "z": 0,
    "sa_1": 0.43434704830053666,
    "sa_2": 0.34203935599284435,
    "sa_3": 0.18032200357781752,
    "sa_4": 0.04329159212880143
  },
  {
    "year": 1991,
    "z": 1,
    "sa_1": 0.38634788634788636,
    "sa_2": 0.3562023562023562,
    "sa_3": 0.19577269577269577,
    "sa_4": 0.061677061677061676
  },
  {
    "year": 1992,
    "z": 0,
    "sa_1": 0.41744031830238726,
    "sa_2": 0.3657161803713528,
    "sa_3": 0.17440318302387267,
    "sa_4": 0.042440318302387266
  },
  {
    "year": 1992,
    "z": 1,
    "sa_1": 0.37118590751808744,
    "sa_2": 0.3790500157282164,
    "sa_3": 0.1925133689839572,
    "sa_4": 0.05725070776973891
  },
  {
    "year": 1993,
    "z": 0,
    "sa_1": 0.3895641861844056,
    "sa_2": 0.3880818262674177,
    "sa_3": 0.1737325822709754,
    "sa_4": 0.0486214052772013
  },
  {
    "year": 1993,
    "z": 1,
    "sa_1": 0.3463976945244957,
    "sa_2": 0.3976945244956772,
    "sa_3": 0.20547550432276657,
    "sa_4": 0.05043227665706052
  },
  {
    "year": 1994,
    "z": 0,
    "sa_1": 0.4058011827654182,
    "sa_2": 0.37031822021965644,
    "sa_3": 0.17769642354266404,
    "sa_4": 0.046184173472261336
  },
  {
    "year": 1994,
    "z": 1,
    "sa_1": 0.3420847413569015,
    "sa_2": 0.3906940473095919,
    "sa_3": 0.19677670912399273,
    "sa_4": 0.07044450220951391
  },
  {
    "year": 1995,
    "z": 0,
    "sa_1": 0.3809066922523387,
    "sa_2": 0.3885823938594387,
    "sa_3": 0.1810985847925162,
    "sa_4": 0.049412329095706406
  },
  {
    "year": 1995,
    "z": 1,
    "sa_1": 0.3478559963311167,
    "sa_2": 0.3861499656042192,
    "sa_3": 0.1997248337537262,
    "sa_4": 0.06626920431093786
  },
  {
    "year": 1996,
    "z": 0,
    "sa_1": 0.36999305394767307,
    "sa_2": 0.3968511229451262,
    "sa_3": 0.18244964112062978,
    "sa_4": 0.05070618198657097
  },
  {
    "year": 1996,
    "z": 1,
    "sa_1": 0.319763624425476,
    "sa_2": 0.39986868023637556,
    "sa_3": 0.21448894725322828,
    "sa_4": 0.06587874808492011
  },
  {
    "year": 1997,
    "z": 0,
    "sa_1": 0.3585176085176085,
    "sa_2": 0.3841113841113841,
    "sa_3": 0.2018837018837019,
    "sa_4": 0.05548730548730549
  },
  {
    "year": 1997,
    "z": 1,
    "sa_1": 0.3059687441159857,
    "sa_2": 0.3897571078892864,
    "sa_3": 0.22952363020146865,
    "sa_4": 0.07475051779325928
  },
  {
    "year": 1998,
    "z": 0,
    "sa_1": 0.35112625402233577,
    "sa_2": 0.3819799356426273,
    "sa_3": 0.20442930153321975,
    "sa_4": 0.06246450880181715
  },
  {
    "year": 1998,
    "z": 1,
    "sa_1": 0.2971358285011422,
    "sa_2": 0.3925496397821121,
    "sa_3": 0.22667369530838166,
    "sa_4": 0.08364083640836409
  },
  {
    "year": 1999,
    "z": 0,
    "sa_1": 0.33571304196413027,
    "sa_2": 0.40397005049625634,
    "sa_3": 0.20337802542225317,
    "sa_4": 0.056938882117360264
  },
  {
    "year": 1999,
    "z": 1,
    "sa_1": 0.2878016746018716,
    "sa_2": 0.3887703168609424,
    "sa_3": 0.24166803480545065,
    "sa_4": 0.08175997373173535
  },
  {
    "year": 2000,
    "z": 0,
    "sa_1": 0.32816579634464754,
    "sa_2": 0.3947454308093995,
    "sa_3": 0.21132506527415143,
    "sa_4": 0.06576370757180157
  },
  {
    "year": 2000,
    "z": 1,
    "sa_1": 0.28863499699338546,
    "sa_2": 0.3949188214070956,
    "sa_3": 0.23015634395670476,
    "sa_4": 0.08628983764281419
  },
  {
    "year": 2001,
    "z": 0,
    "sa_1": 0.3220681686886193,
    "sa_2": 0.3912478336221837,
    "sa_3": 0.21634893125361063,
    "sa_4": 0.07033506643558636
  },
  {
    "year": 2001,
    "z": 1,
    "sa_1": 0.2799728445349627,
    "sa_2": 0.38316361167685,
    "sa_3": 0.23869653767820773,
    "sa_4": 0.09816700610997964
  },
  {
    "year": 2002,
    "z": 0,
    "sa_1": 0.30649483220620133,
    "sa_2": 0.4106163072604313,
    "sa_3": 0.2160265407681511,
    "sa_4": 0.06686231976521628
  },
  {
    "year": 2002,
    "z": 1,
    "sa_1": 0.2770386794777039,
    "sa_2": 0.39073663463907365,
    "sa_3": 0.2423010593742301,
    "sa_4": 0.08992362650899237
  },
  {
    "year": 2003,
    "z": 0,
    "sa_1": 0.3032235621521336,
    "sa_2": 0.38937847866419295,
    "sa_3": 0.22448979591836735,
    "sa_4": 0.08290816326530612
  },
  {
    "year": 2003,
    "z": 1,
    "sa_1": 0.26972496548794733,
    "sa_2": 0.3869597536370394,
    "sa_3": 0.24137198683232453,
    "sa_4": 0.10194329404268876
  },
  {
    "year": 2004,
    "z": 0,
    "sa_1": 0.2926431628286122,
    "sa_2": 0.390462604442633,
    "sa_3": 0.23109843081312412,
    "sa_4": 0.08579580191563073
  },
  {
    "year": 2004,
    "z": 1,
    "sa_1": 0.2639593908629442,
    "sa_2": 0.38859680928208845,
    "sa_3": 0.24238578680203046,
    "sa_4": 0.10505801305293691
  },
  {
    "year": 2005,
    "z": 0,
    "sa_1": 0.27786855482933914,
    "sa_2": 0.39179375453885257,
    "sa_3": 0.2372004357298475,
    "sa_4": 0.09313725490196079
  },
  {
    "year": 2005,
    "z": 1,
    "sa_1": 0.2552620545073375,
    "sa_2": 0.3881761006289308,
    "sa_3": 0.2459538784067086,
    "sa_4": 0.11060796645702306
  },
  {
    "year": 2006,
    "z": 0,
    "sa_1": 0.2801976121860848,
    "sa_2": 0.3880609304240428,
    "sa_3": 0.23548785508439687,
    "sa_4": 0.0962536023054755
  },
  {
    "year": 2006,
    "z": 1,
    "sa_1": 0.2516390423572744,
    "sa_2": 0.3803314917127072,
    "sa_3": 0.2469244935543278,
    "sa_4": 0.12110497237569061
  },
  {
    "year": 2007,
    "z": 0,
    "sa_1": 0.2681842987448351,
    "sa_2": 0.39424651126529975,
    "sa_3": 0.24004053948701956,
    "sa_4": 0.09752865050284557
  },
  {
    "year": 2007,
    "z": 1,
    "sa_1": 0.23908424155185415,
    "sa_2": 0.39029405716635823,
    "sa_3": 0.2543697306189595,
    "sa_4": 0.11625197066282816
  },
  {
    "year": 2008,
    "z": 0,
    "sa_1": 0.2671948145480735,
    "sa_2": 0.3855959668707238,
    "sa_3": 0.24760532949225783,
    "sa_4": 0.09960388908894491
  },
  {
    "year": 2008,
    "z": 1,
    "sa_1": 0.2283062355945929,
    "sa_2": 0.3822338503706472,
    "sa_3": 0.2664922444402915,
    "sa_4": 0.12296766959446832
  },
  {
    "year": 2009,
    "z": 0,
    "sa_1": 0.2655656922154891,
    "sa_2": 0.3918226010521409,
    "sa_3": 0.24339082373310247,
    "sa_4": 0.0992208829992675
  },
  {
    "year": 2009,
    "z": 1,
    "sa_1": 0.2332331174838113,
    "sa_2": 0.3814754856614246,
    "sa_3": 0.2647432932469935,
    "sa_4": 0.12054810360777059
  },
  {
    "year": 2010,
    "z": 0,
    "sa_1": 0.2607167955024596,
    "sa_2": 0.3934709001469367,
    "sa_3": 0.24838689069188016,
    "sa_4": 0.09742541365872356
  },
  {
    "year": 2010,
    "z": 1,
    "sa_1": 0.22217896668705855,
    "sa_2": 0.3922473722262388,
    "sa_3": 0.26756020243590456,
    "sa_4": 0.11801345865079807
  },
  {
    "year": 2011,
    "z": 0,
    "sa_1": 0.2443677219263854,
    "sa_2": 0.3992626835976359,
    "sa_3": 0.25320381531979635,
    "sa_4": 0.10316577915618234
  },
  {
    "year": 2011,
    "z": 1,
    "sa_1": 0.2137388785433478,
    "sa_2": 0.39168218497827434,
    "sa_3": 0.27576039726877716,
    "sa_4": 0.11881853920960066
  },
  {
    "year": 2012,
    "z": 0,
    "sa_1": 0.2444636678200692,
    "sa_2": 0.39261822376009226,
    "sa_3": 0.2549019607843137,
    "sa_4": 0.10801614763552479
  },
  {
    "year": 2012,
    "z": 1,
    "sa_1": 0.20848727422003285,
    "sa_2": 0.38911124794745483,
    "sa_3": 0.27575944170771755,
    "sa_4": 0.12664203612479474
  },
  {
    "year": 2013,
    "z": 0,
    "sa_1": 0.23565443513435425,
    "sa_2": 0.3901762496388327,
    "sa_3": 0.257960127130887,
    "sa_4": 0.11620918809592604
  },
  {
    "year": 2013,
    "z": 1,
    "sa_1": 0.2092479674796748,
    "sa_2": 0.39181910569105693,
    "sa_3": 0.27764227642276423,
    "sa_4": 0.12129065040650407
  },
  {
    "year": 2014,
    "z": 0,
    "sa_1": 0.23028319981947423,
    "sa_2": 0.39298206025047955,
    "sa_3": 0.2634548121403588,
    "sa_4": 0.11327992778968747
  },
  {
    "year": 2014,
    "z": 1,
    "sa_1": 0.2102287737095155,
    "sa_2": 0.38870396787657846,
    "sa_3": 0.2792307285887885,
    "sa_4": 0.12183652982511756
  },
  {
    "year": 2015,
    "z": 0,
    "sa_1": 0.22548684660061497,
    "sa_2": 0.39414645256804465,
    "sa_3": 0.2687051588657328,
    "sa_4": 0.11166154196560756
  },
  {
    "year": 2015,
    "z": 1,
    "sa_1": 0.20303079680625713,
    "sa_2": 0.3892238335777524,
    "sa_3": 0.2837977296181631,
    "sa_4": 0.12394763999782739
  },
  {
    "year": 2016,
    "z": 0,
    "sa_1": 0.23136920358296265,
    "sa_2": 0.39863506184875996,
    "sa_3": 0.2599475961245506,
    "sa_4": 0.11004813844372677
  },
  {
    "year": 2016,
    "z": 1,
    "sa_1": 0.1979828165857303,
    "sa_2": 0.39537862212498,
    "sa_3": 0.28459362826191364,
    "sa_4": 0.12204493302737605
  },
  {
    "year": 2017,
    "z": 0,
    "sa_1": 0.23779400770602105,
    "sa_2": 0.3900741848294899,
    "sa_3": 0.2611996089481856,
    "sa_4": 0.11093219851630341
  },
  {
    "year": 2017,
    "z": 1,
    "sa_1": 0.20828424381472066,
    "sa_2": 0.3879828858436163,
    "sa_3": 0.27810504123519564,
    "sa_4": 0.12562782910646741
  },
  {
    "year": 2018,
    "z": 0,
    "sa_1": 0.2267881241565452,
    "sa_2": 0.3883940620782726,
    "sa_3": 0.2705128205128205,
    "sa_4": 0.11430499325236167
  },
  {
    "year": 2018,
    "z": 1,
    "sa_1": 0.2041568485287898,
    "sa_2": 0.3917588061144342,
    "sa_3": 0.2831248867137937,
    "sa_4": 0.1209594586429823
  }
]